machine_usage/__init__.py
machine_usage/app.py
machine_usage/argparse.py
machine_usage/collect_data.py
machine_usage/header.py
machine_usage/info.py
machine_usage/procs_list.py
machine_usage/user_stat.py
machine_usage-0.1.3.dist-info/METADATA
machine_usage-0.1.3.dist-info/WHEEL
machine_usage-0.1.3.dist-info/entry_points.txt
machine_usage-0.1.3.dist-info/top_level.txt
machine_usage-0.1.3.dist-info/RECORD
