Metadata-Version: 2.1
Name: machine-usage
Version: 0.1.3
Summary: Display the available resources on our local cluster.
Home-page: https://github.com/marrink-lab/machine_usage
Author: Jan A. Stevens
Author-email: stevens.jan.adriaan@gmail.com
License: UNKNOWN
Platform: UNKNOWN
Requires-Python: >=3.7
Requires-Dist: click
Requires-Dist: textual
Requires-Dist: distro
